Workbook

Sheet TCS
B12: TCS Company Valuation

Sheet P&L
B2: Profit & Loss | P2: YOY % | Q2: YOY % | R2: Average Return %
C3: 42064 | D3: 42430 | E3: 42795 | F3: 43160 | G3: 43525 | H3: 43891 | I3: 44256 | J3: 44621 | K3: 44986 | L3: 45352 | M3: 45717 | N3: 46082 | P3: 26-25 | Q3: 25-24 | R3: Avg. | T3: 46447 | U3: 46813 | V3: 47178 | W3: 47543 | X3: 47908
B4: Sales | C4: 94648 | D4: 108646 | E4: 117966 | F4: 123104 | G4: 146463 | H4: 156949 | I4: 164177 | J4: 191754 | K4: 225458 | L4: 240893 | M4: 255324 | N4: 267021 | P4: =(N4-M4)/M4 -> 0.04581238 | Q4: =(M4-L4)/L4 -> 0.059906265 | R4: =AVERAGE(P4:Q4) -> 0.052859323 | T4: =N4*(1+R4) -> 281135.55 | U4: =T4*(1+$R$4) -> 295996.18 | V4: =U4*(1+$R$4) -> 311642.34 | W4: =V4*(1+$R$4) -> 328115.54 | X4: =W4*(1+$R$4) -> 345459.51
B5: Expenses | C5: 70167 | D5: 77969 | E5: 85655 | F5: 90588 | G5: 106957 | H5: 114840 | I5: 117631 | J5: 138697 | K5: 166199 | L5: 176597 | M5: 187917 | N5: 194623 | P5: =(N5-M5)/M5 -> 0.035685968 | Q5: =(M5-L5)/L5 -> 0.064100749 | R5: =AVERAGE(P5:Q5) -> 0.049893358 | T5: =N5*(1+R5) -> 204333.4 | U5: =T5*(1+$R$5) -> 214528.27 | V5: =U5*(1+$R$5) -> 225231.81 | W5: =V5*(1+$R$5) -> 236469.38 | X5: =W5*(1+$R$5) -> 248267.63
B6: Operating Profit | C6: 24482 | D6: 30677 | E6: 32311 | F6: 32516 | G6: 39506 | H6: 42109 | I6: 46546 | J6: 53057 | K6: 59259 | L6: 64296 | M6: 67407 | N6: 72398 | P6: =(N6-M6)/M6 -> 0.074042755 | Q6: =(M6-L6)/L6 -> 0.048385592 | R6: =AVERAGE(P6:Q6) -> 0.061214173 | T6: =N6*(1+R6) -> 76829.784 | U6: =T6*(1+$R$6) -> 81532.855 | V6: =U6*(1+$R$6) -> 86523.822 | W6: =V6*(1+$R$6) -> 91820.306 | X6: =W6*(1+$R$6) -> 97441.01
B7: OPM % | C7: 0.26 | D7: 0.28 | E7: 0.27 | F7: 0.26 | G7: 0.27 | H7: 0.27 | I7: 0.28 | J7: 0.28 | K7: 0.26 | L7: 0.27 | M7: 0.26 | N7: 0.27
B8: Other Income | C8: 3720 | D8: 3084 | E8: 4221 | F8: 3642 | G8: 4311 | H8: 4592 | I8: 1916 | J8: 4018 | K8: 3449 | L8: 3464 | M8: 3962 | N8: -124 | P8: =(N8-M8)/M8 -> -1.0312973 | Q8: =(M8-L8)/L8 -> 0.14376443 | R8: =AVERAGE(P8:Q8) -> -0.44376645 | T8: =N8*(1+R8) -> -68.972961 | U8: =T8*(1+$R$8) -> -38.365075 | V8: =U8*(1+$R$8) -> -21.339942 | W8: =V8*(1+$R$8) -> -11.869992 | X8: =W8*(1+$R$8) -> -6.6024878
B9: Interest | C9: 104 | D9: 33 | E9: 32 | F9: 52 | G9: 198 | H9: 924 | I9: 637 | J9: 784 | K9: 779 | L9: 778 | M9: 796 | N9: 1227 | P9: =(N9-M9)/M9 -> 0.54145729 | Q9: =(M9-L9)/L9 -> 0.023136247 | R9: =AVERAGE(P9:Q9) -> 0.28229677 | T9: =N9*(1+R9) -> 1573.3781 | U9: =T9*(1+$R$9) -> 2017.5377 | V9: =U9*(1+$R$9) -> 2587.0821 | W9: =V9*(1+$R$9) -> 3317.407 | X9: =W9*(1+$R$9) -> 4253.9002
B10: Depreciation | C10: 1799 | D10: 1888 | E10: 1987 | F10: 2014 | G10: 2056 | H10: 3529 | I10: 4065 | J10: 4604 | K10: 5022 | L10: 4985 | M10: 5242 | N10: 5560 | P10: =(N10-M10)/M10 -> 0.060663869 | Q10: =(M10-L10)/L10 -> 0.051554664 | R10: =AVERAGE(P10:Q10) -> 0.056109266 | T10: =N10*(1+R10) -> 5871.9675 | U10: =T10*(1+$R$10) -> 6201.4393 | V10: =U10*(1+$R$10) -> 6549.3975 | W10: =V10*(1+$R$10) -> 6916.8794 | X10: =W10*(1+$R$10) -> 7304.9804
B11: Profit before tax | C11: 26298 | D11: 31840 | E11: 34513 | F11: 34092 | G11: 41563 | H11: 42248 | I11: 43760 | J11: 51687 | K11: 56907 | L11: 61997 | M11: 65331 | N11: 65487 | P11: =(N11-M11)/M11 -> 0.0023878404 | Q11: =(M11-L11)/L11 -> 0.053776796 | R11: =AVERAGE(P11:Q11) -> 0.028082318 | T11: =N11*(1+R11) -> 67326.027 | U11: =T11*(1+$R$11) -> 69216.698 | V11: =U11*(1+$R$11) -> 71160.463 | W11: =V11*(1+$R$11) -> 73158.814 | X11: =W11*(1+$R$11) -> 75213.283
B12: Tax % | C12: 0.24 | D12: 0.24 | E12: 0.24 | F12: 0.24 | G12: 0.24 | H12: 0.23 | I12: 0.26 | J12: 0.26 | K12: 0.26 | L12: 0.26 | M12: 0.25 | N12: 0.24
B13: Net Profit | C13: 20060 | D13: 24338 | E13: 26357 | F13: 25880 | G13: 31562 | H13: 32447 | I13: 32562 | J13: 38449 | K13: 42303 | L13: 46099 | M13: 48797 | N13: 49454 | P13: =(N13-M13)/M13 -> 0.013463942 | Q13: =(M13-L13)/L13 -> 0.058526215 | R13: =AVERAGE(P13:Q13) -> 0.035995079 | T13: =N13*(1+R13) -> 51234.101 | U13: =T13*(1+$R$13) -> 53078.276 | V13: =U13*(1+$R$13) -> 54988.833 | W13: =V13*(1+$R$13) -> 56968.16 | X13: =W13*(1+$R$13) -> 59018.734
B14: EPS in Rs | C14: 50.68 | D14: 61.58 | E14: 66.71 | F14: 67.46 | G14: 83.87 | H14: 86.19 | I14: 87.67 | J14: 104.75 | K14: 115.19 | L14: 126.88 | M14: 134.2 | N14: 136.01 | P14: =(N14-M14)/M14 -> 0.013487332 | Q14: =(M14-L14)/L14 -> 0.057692308 | R14: =AVERAGE(P14:Q14) -> 0.03558982 | T14: =N14*(1+R14) -> 140.85057 | U14: =T14*(1+$R$14) -> 145.86342 | V14: =U14*(1+$R$14) -> 151.05467 | W14: =V14*(1+$R$14) -> 156.43068 | X14: =W14*(1+$R$14) -> 161.99802
B15: Dividend Payout % | C15: 0.78 | D15: 0.35 | E15: 0.35 | F15: 0.37 | G15: 0.36 | H15: 0.85 | I15: 0.43 | J15: 0.41 | K15: 1 | L15: 0.58 | M15: 0.94 | N15: 0.81
B18: Compounded Sales Growth
B19: 10 Years: | C19: 0.09
B20: 5 Years: | C20: 0.1
B21: 3 Years: | C21: 0.06
B22: TTM: | C22: 0.08
B24: Compounded Profit Growth
B25: 10 Years: | C25: 0.08
B26: 5 Years: | C26: 0.09
B27: 3 Years: | C27: 0.08
B28: TTM: | C28: 0.09
B30: Stock Price CAGR
B31: 10 Years: | C31: 0.06
B32: 5 Years: | C32: -0.12
B33: 3 Years: | C33: -0.16
B34: 1 Year: | C34: -0.31
B36: Return on Equity
B37: 10 Years: | C37: 0.43
B38: 5 Years: | C38: 0.49
B39: 3 Years: | C39: 0.52
B40: Last Year: | C40: 0.52

Sheet P&L Detail
B2: Profit & Loss Detail
C3: 42064 | D3: 42430 | E3: 42795 | F3: 43160 | G3: 43525 | H3: 43891 | I3: 44256 | J3: 44621 | K3: 44986 | L3: 45352 | M3: 45717 | N3: 46082
B4: Sales | C4: 94648 | D4: 108646 | E4: 117966 | F4: 123104 | G4: 146463 | H4: 156949 | I4: 164177 | J4: 191754 | K4: 225458 | L4: 240893 | M4: 255324 | N4: 267021
B5: Sales Growth % | C5: 0.1569 | D5: 0.1479 | E5: 0.0858 | F5: 0.0436 | G5: 0.1898 | H5: 0.0716 | I5: 0.0461 | J5: 0.168 | K5: 0.1758 | L5: 0.0685 | M5: 0.0599 | N5: 0.0458
B6: Expenses | C6: 70167 | D6: 77969 | E6: 85655 | F6: 90588 | G6: 106957 | H6: 114840 | I6: 117631 | J6: 138697 | K6: 166199 | L6: 176597 | M6: 187917 | N6: 194623
B7: Material Cost % | C7: 0 | D7: 0 | E7: 0 | F7: 0 | G7: 0 | H7: 0 | I7: 0 | J7: 0 | K7: 0 | L7: 0 | M7: 0 | N7: 0
B8: Manufacturing Cost % | C8: 0.26 | D8: 0.02 | E8: 0.02 | F8: 0.02 | G8: 0.02 | H8: 0.01 | I8: 0.01 | J8: 0.01 | K8: 0.01 | L8: 0.02 | M8: 0.05 | N8: 0.02
B9: Employee Cost % | C9: 0.41 | D9: 0.51 | E9: 0.52 | F9: 0.54 | G9: 0.53 | H9: 0.55 | I9: 0.56 | J9: 0.56 | K9: 0.57 | L9: 0.58 | M9: 0.57 | N9: 0.58
B10: Other Cost % | C10: 0.07 | D10: 0.18 | E10: 0.18 | F10: 0.17 | G10: 0.18 | H10: 0.17 | I10: 0.15 | J10: 0.16 | K10: 0.16 | L10: 0.14 | M10: 0.12 | N10: 0.13
B11: Operating Profit | C11: 24482 | D11: 30677 | E11: 32311 | F11: 32516 | G11: 39506 | H11: 42109 | I11: 46546 | J11: 53057 | K11: 59259 | L11: 64296 | M11: 67407 | N11: 72398
B12: OPM % | C12: 0.26 | D12: 0.28 | E12: 0.27 | F12: 0.26 | G12: 0.27 | H12: 0.27 | I12: 0.28 | J12: 0.28 | K12: 0.26 | L12: 0.27 | M12: 0.26 | N12: 0.27
B13: Other Income | C13: 3720 | D13: 3084 | E13: 4221 | F13: 3642 | G13: 4311 | H13: 4592 | I13: 1916 | J13: 4018 | K13: 3449 | L13: 3464 | M13: 3962 | N13: -124
B14: Exceptional items | C14: 725 | D14: 470 | E14: 12 | F14: 225 | G14: 84 | H14: 60 | I14: -1205 | J14: 23 | K14: 30 | L14: -933 | M14: 31 | N14: -4176
B15: Other income normal | C15: 2994 | D15: 2614 | E15: 4209 | F15: 3417 | G15: 4227 | H15: 4532 | I15: 3121 | J15: 3995 | K15: 3419 | L15: 4397 | M15: 3931 | N15: 4052
... B28: Dividend Payout % | C28: 0.78 | D28: 0.35 | E28: 0.35 | F28: 0.37 | G28: 0.36 | H28: 0.85 | I28: 0.43 | J28: 0.41 | K28: 1 | L28: 0.58 | M28: 0.94 | N28: 0.81

Sheet Balance sheet
B2: Balance Sheet | P2: YOY % | Q2: YOY % | R2: Average Return %
C3: 42064 | D3: 42430 | E3: 42795 | F3: 43160 | G3: 43525 | H3: 43891 | I3: 44256 | J3: 44621 | K3: 44986 | L3: 45352 | M3: 45717 | N3: 46082 | P3: 26-25 | Q3: 25-24 | R3: Avg. | T3: 46447 | U3: 46813 | V3: 47178 | W3: 47543 | X3: 47908
B4: Equity Capital | C4: 196 | D4: 197 | E4: 197 | F4: 191 | G4: 375 | H4: 375 | I4: 370 | J4: 366 | K4: 366 | L4: 362 | M4: 362 | N4: 362 | P4: =(N4-M4)/M4 -> 0 | Q4: =(M4-L4)/L4 -> 0 | R4: =AVERAGE(P4:Q4) -> 0 | T4: =N4*(1+$R$4) -> 362 | U4: =T4*(1+R4) -> 362 | V4: =U4*(1+$R$4) -> 362 | W4: =V4*(1+$R$4) -> 362 | X4: =W4*(1+$R$4) -> 362
B5: Reserves | C5: 50439 | D5: 70875 | E5: 86017 | F5: 84937 | G5: 89071 | H5: 83751 | I5: 86063 | J5: 88773 | K5: 90058 | L5: 90127 | M5: 94394 | N5: 106878 | P5: =(N5-M5)/M5 -> 0.13225417 | Q5: =(M5-L5)/L5 -> 0.047344303 | R5: =AVERAGE(P5:Q5) -> 0.089799236 | T5: =N5*(1+R5) -> 116475.56 | U5: =T5*(1+$R$5) -> 126934.98 | V5: =U5*(1+$R$5) -> 138333.64 | W5: =V5*(1+$R$5) -> 150755.9 | X5: =W5*(1+$R$5) -> 164293.66
B6: Borrowings | C6: 358 | D6: 245 | E6: 289 | F6: 247 | G6: 62 | H6: 8174 | I6: 7795 | J6: 7818 | K6: 7688 | L6: 8021 | M6: 9392 | N6: 11283 | P6: =(N6-M6)/M6 -> 0.20134157 | Q6: =(M6-L6)/L6 -> 0.17092632 | R6: =AVERAGE(P6:Q6) -> 0.18613394 | T6: =N6*(1+R6) -> 13383.149 | U6: =T6*(1+$R$6) -> 15874.208 | V6: =U6*(1+$R$6) -> 18828.936 | W6: =V6*(1+$R$6) -> 22333.641 | X6: =W6*(1+$R$6) -> 26490.689
B7: Other Liabilities | C7: 22325 | D7: 16974 | E7: 15830 | F7: 19751 | G7: 24393 | H7: 27827 | I7: 35764 | J7: 43967 | K7: 44747 | L7: 46962 | M7: 54501 | N7: 62644 | P7: =(N7-M7)/M7 -> 0.1494101 | Q7: =(M7-L7)/L7 -> 0.16053405 | R7: =AVERAGE(P7:Q7) -> 0.15497208 | T7: =N7*(1+R7) -> 72352.071 | U7: =T7*(1+$R$7) -> 83564.621 | V7: =U7*(1+$R$7) -> 96514.804 | W7: =V7*(1+$R$7) -> 111471.9 | X7: =W7*(1+$R$7) -> 128746.94
B8: Total Liabilities | C8: 73318 | D8: 88291 | E8: 102333 | F8: 105126 | G8: 113901 | H8: 120127 | I8: 129992 | J8: 140924 | K8: 142859 | L8: 145472 | M8: 158649 | N8: 181167 | P8: =(N8-M8)/M8 -> 0.14193597 | Q8: =(M8-L8)/L8 -> 0.090581005 | R8: =AVERAGE(P8:Q8) -> 0.11625849 | T8: =N8*(1+R8) -> 202229.2 | U8: =T8*(1+$R$8) -> 225740.06 | V8: =U8*(1+$R$8) -> 251984.26 | W8: =V8*(1+$R$8) -> 281279.57 | X8: =W8*(1+$R$8) -> 313980.71
B9: Fixed Assets | C9: 11638 | D9: 11774 | E9: 11701 | F9: 11973 | G9: 12290 | H9: 20928 | I9: 21021 | J9: 21298 | K9: 20515 | L9: 19604 | M9: 23053 | N9: 31343 | P9: =(N9-M9)/M9 -> 0.35960613 | Q9: =(M9-L9)/L9 -> 0.17593348 | R9: =AVERAGE(P9:Q9) -> 0.2677698 | T9: =N9*(1+R9) -> 39735.709 | U9: =T9*(1+$R$9) -> 50375.732 | V9: =U9*(1+$R$9) -> 63864.832 | W9: =V9*(1+$R$9) -> 80965.905 | X9: =W9*(1+$R$9) -> 102646.13
B10: CWIP | C10: 2766 | D10: 1670 | E10: 1541 | F10: 1278 | G10: 963 | H10: 906 | I10: 926 | J10: 1205 | K10: 1234 | L10: 1564 | M10: 1546 | N10: 2665 | P10: =(N10-M10)/M10 -> 0.72380336 | Q10: =(M10-L10)/L10 -> -0.011508951 | R10: =AVERAGE(P10:Q10) -> 0.35614721 | T10: =N10*(1+R10) -> 3614.1323 | U10: =T10*(1+$R$10) -> 4901.2954 | V10: =U10*(1+$R$10) -> 6646.8781 | W10: =V10*(1+$R$10) -> 9014.1452 | X10: =W10*(1+$R$10) -> 12224.508
B11: Investments | C11: 1662 | D11: 22822 | E11: 41980 | F11: 36008 | G11: 29330 | H11: 26356 | I11: 29373 | J11: 30485 | K11: 37163 | L11: 31762 | M11: 30964 | N11: 33988 | P11: =(N11-M11)/M11 -> 0.097661801 | Q11: =(M11-L11)/L11 -> -0.025124362 | R11: =AVERAGE(P11:Q11) -> 0.036268719 | T11: =N11*(1+R11) -> 35220.701 | U11: =T11*(1+$R$11) -> 36498.111 | V11: =U11*(1+$R$11) -> 37821.851 | W11: =V11*(1+$R$11) -> 39193.601 | X11: =W11*(1+$R$11) -> 40615.102
B12: Other Assets | C12: 57252 | D12: 52025 | E12: 47111 | F12: 55867 | G12: 71318 | H12: 71937 | I12: 78672 | J12: 87936 | K12: 83947 | L12: 92542 | M12: 103086 | N12: 113171 | P12: =(N12-M12)/M12 -> 0.097830937 | Q12: =(M12-L12)/L12 -> 0.11393746 | R12: =AVERAGE(P12:Q12) -> 0.1058842 | T12: =N12*(1+R12) -> 125154.02 | U12: =T12*(1+$R$12) -> 138405.85 | V12: =U12*(1+$R$12) -> 153060.85 | W12: =V12*(1+$R$12) -> 169267.57 | X12: =W12*(1+$R$12) -> 187190.33
B13: Total Assets | C13: 73318 | D13: 88291 | E13: 102333 | F13: 105126 | G13: 113901 | H13: 120127 | I13: 129992 | J13: 140924 | K13: 142859 | L13: 145472 | M13: 158649 | N13: 181167 | P13: =(N13-M13)/M13 -> 0.14193597 | Q13: =(M13-L13)/L13 -> 0.090581005 | R13: =AVERAGE(P13:Q13) -> 0.11625849 | T13: =N13*(1+R13) -> 202229.2 | U13: =T13*(1+$R$13) -> 225740.06 | V13: =U13*(1+$R$13) -> 251984.26 | W13: =V13*(1+$R$13) -> 281279.57 | X13: =W13*(1+$R$13) -> 313980.71

Sheet Balance Sheet Detail
B2: Balance Sheet Detail
C3: 42064 | D3: 42430 | E3: 42795 | F3: 43160 | G3: 43525 | H3: 43891 | I3: 44256 | J3: 44621 | K3: 44986 | L3: 45352 | M3: 45717 | N3: 46082
B4: Equity Capital | C4: 196 | D4: 197 | E4: 197 | F4: 191 | G4: 375 | H4: 375 | I4: 370 | J4: 366 | K4: 366 | L4: 362 | M4: 362 | N4: 362
B5: Reserves | C5: 50439 | D5: 70875 | E5: 86017 | F5: 84937 | G5: 89071 | H5: 83751 | I5: 86063 | J5: 88773 | K5: 90058 | L5: 90127 | M5: 94394 | N5: 106878
B6: Borrowings | C6: 358 | D6: 245 | E6: 289 | F6: 247 | G6: 62 | H6: 8174 | I6: 7795 | J6: 7818 | K6: 7688 | L6: 8021 | M6: 9392 | N6: 11283
B7: Long term Borrowings | C7: 114 | D7: 83 | E7: 71 | F7: 54 | G7: 44 | H7: 0 | I7: 0 | J7: 0 | K7: 0 | L7: 0 | M7: 0 | N7: 0
B8: Short term Borrowings | C8: 186 | D8: 113 | E8: 200 | F8: 181 | G8: 0 | H8: 0 | I8: 0 | J8: 0 | K8: 0 | L8: 0 | M8: 0 | N8: 0
B9: Lease Liabilities | C9: 0 | D9: 0 | E9: 0 | F9: 0 | G9: 44 | H9: 8174 | I9: 7795 | J9: 7818 | K9: 7688 | L9: 8021 | M9: 9392 | N9: 11283
B10: Other Borrowings | C10: 58 | D10: 49 | E10: 18 | F10: 12 | G10: -26 | H10: 0 | I10: 0 | J10: 0 | K10: 0 | L10: 0 | M10: 0 | N10: 0
B11: Other Liabilities | C11: 22325 | D11: 16974 | E11: 15830 | F11: 19751 | G11: 24393 | H11: 27827 | I11: 35764 | J11: 43967 | K11: 44747 | L11: 46962 | M11: 54501 | N11: 62644
B12: Non controlling int | C12: 1128 | D12: 355 | E12: 366 | F12: 402 | G12: 453 | H12: 623 | I12: 675 | J12: 707 | K12: 782 | L12: 830 | M12: 1015 | N12: 1238
B13: Trade Payables | C13: 8831 | D13: 7541 | E13: 4905 | F13: 5094 | G13: 6292 | H13: 6740 | I13: 7860 | J13: 8045 | K13: 10515 | L13: 9981 | M13: 13909 | N13: 14808
B14: Advance from Customers | C14: 131 | D14: 164 | E14: 330 | F14: 796 | G14: 575 | H14: 345 | I14: 312 | J14: 468 | K14: 543 | L14: 1841 | M14: 1896 | N14: 694
B15: Other liability items | C15: 12236 | D15: 8914 | E15: 10229 | F15: 13459 | G15: 17073 | H15: 20119 | I15: 26917 | J15: 34747 | K15: 32907 | L15: 34310 | M15: 37681 | N15: 45904
... B40: Total Assets | C40: 73318 | D40: 88291 | E40: 102333 | F40: 105126 | G40: 113901 | H40: 120127 | I40: 129992 | J40: 140924 | K40: 142859 | L40: 145472 | M40: 158649 | N40: 181167

Sheet Cash Flow 
B2: Cash Flows | P2: YOY % | Q2: YOY % | R2: Average Return %
C3: 42064 | D3: 42430 | E3: 42795 | F3: 43160 | G3: 43525 | H3: 43891 | I3: 44256 | J3: 44621 | K3: 44986 | L3: 45352 | M3: 45717 | N3: 46082 | P3: 26-25 | Q3: 25-24 | R3: Avg. | T3: 46447 | U3: 46813 | V3: 47178 | W3: 47543 | X3: 47908
B4: Cash from Operating Activity | C4: 19369 | D4: 19109 | E4: 25223 | F4: 25067 | G4: 28593 | H4: 32369 | I4: 38802 | J4: 39949 | K4: 41965 | L4: 44338 | M4: 48908 | N4: 52094 | P4: =(N4-M4)/M4 -> 0.065142717 | Q4: =(M4-L4)/L4 -> 0.10307186 | R4: =AVERAGE(P4:Q4) -> 0.084107287 | T4: =N4*(1+R4) -> 56475.485 | U4: =T4*(1+$R$4) -> 61225.485 | V4: =U4*(1+$R$4) -> 66374.994 | W4: =V4*(1+$R$4) -> 71957.615 | X4: =W4*(1+$R$4) -> 78009.775
B5: Cash from Investing Activity | C5: -1807 | D5: -5010 | E5: -16895 | F5: 3104 | G5: 1645 | H5: 8968 | I5: -7956 | J5: -738 | K5: 548 | L5: 6091 | M5: -2144 | N5: -11886 | P5: =(N5-M5)/M5 -> 4.5438433 | Q5: =(M5-L5)/L5 -> -1.3519947 | R5: =AVERAGE(P5:Q5) -> 1.5959243 | T5: =N5*(1+R5) -> -30855.156 | U5: =T5*(1+$R$5) -> -80097.648 | V5: =U5*(1+$R$5) -> -207927.43 | W5: =V5*(1+$R$5) -> -539763.86 | X5: =W5*(1+$R$5) -> -1401186.1
B6: Cash from Financing Activity | C6: -17168 | D6: -9666 | E6: -11026 | F6: -26885 | G6: -27897 | H6: -39915 | I6: -32634 | J6: -33581 | K6: -47878 | L6: -48536 | M6: -47438 | N6: -42133 | P6: =(N6-M6)/M6 -> -0.11183018 | Q6: =(M6-L6)/L6 -> -0.022622383 | R6: =AVERAGE(P6:Q6) -> -0.067226281 | T6: =N6*(1+R6) -> -39300.555 | U6: =T6*(1+$R$6) -> -36658.525 | V6: =U6*(1+$R$6) -> -34194.109 | W6: =V6*(1+$R$6) -> -31895.366 | X6: =W6*(1+$R$6) -> -29751.159
B7: Net Cash Flow | C7: 394 | D7: 4433 | E7: -2698 | F7: 1286 | G7: 2341 | H7: 1422 | I7: -1788 | J7: 5630 | K7: -5365 | L7: 1893 | M7: -674 | N7: -1925 | P7: =(N7-M7)/M7 -> 1.8560831 | Q7: =(M7-L7)/L7 -> -1.3560486 | R7: =AVERAGE(P7:Q7) -> 0.25001724 | T7: =N7*(1+R7) -> -2406.2832 | U7: =T7*(1+$R$7) -> -3007.8955 | V7: =U7*(1+$R$7) -> -3759.9212 | W7: =V7*(1+$R$7) -> -4699.9664 | X7: =W7*(1+$R$7) -> -5875.039
B8: Free Cash Flow | C8: 16426 | D8: 17144 | E8: 23270 | F8: 23263 | G8: 26461 | H8: 29281 | I8: 35663 | J8: 36985 | K8: 38902 | L8: 41688 | M8: 44994 | N8: 48013 | P8: =(N8-M8)/M8 -> 0.067097835 | Q8: =(M8-L8)/L8 -> 0.079303397 | R8: =AVERAGE(P8:Q8) -> 0.073200616 | T8: =N8*(1+R8) -> 51527.581 | U8: =T8*(1+$R$8) -> 55299.432 | V8: =U8*(1+$R$8) -> 59347.384 | W8: =V8*(1+$R$8) -> 63691.649 | X8: =W8*(1+$R$8) -> 68353.917
B9: CFO/OP | C9: 1.1 | D9: 0.87 | E9: 1.03 | F9: 1 | G9: 0.98 | H9: 0.91 | I9: 1.03 | J9: 0.97 | K9: 0.93 | L9: 0.88 | M9: 0.96 | N9: 0.92
B11: Capex
B12: Fixed assets purchased | C12: -2949 | D12: -1987 | E12: -1989 | F12: -1862 | G12: -2231 | H12: -3249 | I12: -3176 | J12: -2995 | K12: -3100 | L12: -2674 | M12: -3937 | N12: -4146 | P12: =(N12-M12)/M12 -> 0.053086106 | Q12: =(M12-L12)/L12 -> 0.4723261 | R12: =AVERAGE(P12:Q12) -> 0.2627061 | T12: =N12*(1+$R$12) -> -5235.1795 | U12: =T12*(1+$R$12) -> -6610.4931 | V12: =U12*(1+$R$12) -> -8347.11 | W12: =V12*(1+$R$12) -> -10539.947 | X12: =W12*(1+$R$12) -> -13308.855

Sheet Cash Flow Detail
B2: Cash Flow Detail
C3: 42064 | D3: 42430 | E3: 42795 | F3: 43160 | G3: 43525 | H3: 43891 | I3: 44256 | J3: 44621 | K3: 44986 | L3: 45352 | M3: 45717 | N3: 46082
B4: Cash from Operating Activity - | C4: 19369 | D4: 19109 | E4: 25223 | F4: 25067 | G4: 28593 | H4: 32369 | I4: 38802 | J4: 39949 | K4: 41965 | L4: 44338 | M4: 48908 | N4: 52094
B5: Profit from operations | C5: 26103 | D5: 31631 | E5: 33800 | F5: 32885 | G5: 40720 | H5: 42882 | I5: 47031 | J5: 54204 | K5: 59148 | L5: 63709 | M5: 67853 | N5: 68688
B6: Receivables | C6: -2158 | D6: -2936 | E6: 680 | F6: -1833 | G6: -2883 | H6: -3295 | I6: 1059 | J6: -5144 | K6: -7683 | L6: -3332 | M6: -5228 | N6: -5248
B7: Inventory | C7: -1 | D7: 0 | E7: 0 | F7: -5 | G7: 16 | H7: 5 | I7: -3 | J7: -12 | K7: -8 | L7: 0 | M7: 7 | N7: -8
B8: Payables | C8: 0 | D8: -2039 | E8: -201 | F8: -346 | G8: 1496 | H8: 446 | I8: -93 | J8: 186 | K8: 2036 | L8: -632 | M8: 3718 | N8: -1105
B9: Loans Advances | C9: -712 | D9: -798 | E9: 0 | F9: 0 | G9: -499 | H9: 0 | I9: -17 | J9: -116 | K9: 261 | L9: -301 | M9: -738 | N9: 197
B10: Other WC items | C10: 3618 | D10: 829 | E10: -1110 | F10: 1975 | G10: -299 | H10: -1823 | I10: -83 | J10: 2317 | K10: 1177 | L10: -2617 | M10: -1118 | N10: 3954
B11: Working capital changes | C11: 747 | D11: -4944 | E11: -631 | F11: -209 | G11: -2169 | H11: -4667 | I11: 863 | J11: -2769 | K11: -4217 | L11: -6882 | M11: -3359 | N11: -2210
B12: Direct taxes | C12: -7482 | D12: -7578 | E12: -7946 | F12: -7609 | G12: -9958 | H12: -5846 | I12: -9092 | J12: -11486 | K12: -12966 | L12: -12489 | M12: -15586 | N12: -14384
B13: Cash from Investing Activity - | C13: -1807 | D13: -5010 | E13: -16895 | F13: 3104 | G13: 1645 | H13: 8968 | I13: -7956 | J13: -738 | K13: 548 | L13: 6091 | M13: -2144 | N13: -11886
B14: Fixed assets purchased | C14: -2949 | D14: -1987 | E14: -1989 | F14: -1862 | G14: -2231 | H14: -3249 | I14: -3176 | J14: -2995 | K14: -3100 | L14: -2674 | M14: -3937 | N14: -4146
B15: Fixed assets sold | C15: 7 | D15: 22 | E15: 36 | F15: 58 | G15: 99 | H15: 161 | I15: 37 | J15: 31 | K15: 37 | L15: 24 | M15: 23 | N15: 65
... B33: CFO/OP | C33: 1.1 | D33: 0.87 | E33: 1.03 | F33: 1 | G33: 0.98 | H33: 0.91 | I33: 1.03 | J33: 0.97 | K33: 0.93 | L33: 0.88 | M33: 0.96 | N33: 0.92

Sheet Working Capital 
B2: Working Capital in Crores
C3: 42064 | D3: 42430 | E3: 42795 | F3: 43160 | G3: 43525 | H3: 43891 | I3: 44256 | J3: 44621 | K3: 44986 | L3: 45352 | M3: 45717 | N3: 46082 | O3: 46447 | P3: 46813 | Q3: 47178 | R3: 47543 | S3: 47908
B4: Current Liabilities
B5: Short term Borrowings | C5: 186 | D5: 113 | E5: 200 | F5: 181 | G5: 0 | H5: 0 | I5: 0 | J5: 0 | K5: 0 | L5: 0 | M5: 0 | N5: 0 | O5: 0 | P5: 0 | Q5: 0 | R5: 0 | S5: 0
B6: Lease Liabilities | C6: 0 | D6: 0 | E6: 0 | F6: 0 | G6: 44 | H6: 8174 | I6: 7795 | J6: 7818 | K6: 7688 | L6: 8021 | M6: 9392 | N6: 11283 | O6: 9565 | P6: 9565 | Q6: 9565 | R6: 9565 | S6: 9565
B7: Trade Payables | C7: 8831 | D7: 7541 | E7: 4905 | F7: 5094 | G7: 6292 | H7: 6740 | I7: 7860 | J7: 8045 | K7: 10515 | L7: 9981 | M7: 13909 | N7: 14808 | O7: ='P&L'!T5*'Working Capital '!O23/365 -> 14073.176 | P7: ='P&L'!U5*'Working Capital '!P23/365 -> 14775.334 | Q7: ='P&L'!V5*'Working Capital '!Q23/365 -> 15512.525 | R7: ='P&L'!W5*'Working Capital '!R23/365 -> 16286.497 | S7: ='P&L'!X5*'Working Capital '!S23/365 -> 17099.085
B8: Advance from Customers | C8: 131 | D8: 164 | E8: 330 | F8: 796 | G8: 575 | H8: 345 | I8: 312 | J8: 468 | K8: 543 | L8: 1841 | M8: 1896 | N8: 694 | O8: =(N8/'P&L'!T4)*'P&L'!T4 -> 694 | P8: =(O8/'P&L'!U4)*'P&L'!U4 -> 694 | Q8: =(P8/'P&L'!V4)*'P&L'!V4 -> 694 | R8: =(Q8/'P&L'!W4)*'P&L'!W4 -> 694 | S8: =(R8/'P&L'!X4)*'P&L'!X4 -> 694
B9: Other liability items | C9: 12236 | D9: 8914 | E9: 10229 | F9: 13459 | G9: 17073 | H9: 20119 | I9: 26917 | J9: 34747 | K9: 32907 | L9: 34310 | M9: 37681 | N9: 45904 | O9: =AVERAGE($L$9:$N$9) -> 39298.333 | P9: =AVERAGE($L$9:$N$9) -> 39298.333 | Q9: =AVERAGE($L$9:$N$9) -> 39298.333 | R9: =AVERAGE($L$9:$N$9) -> 39298.333 | S9: =AVERAGE($L$9:$N$9) -> 39298.333
B10: Total Current Liabilities | C10: =SUM(C5:C9) -> 21384 | D10: =SUM(D5:D9) -> 16732 | E10: =SUM(E5:E9) -> 15664 | F10: =SUM(F5:F9) -> 19530 | G10: =SUM(G5:G9) -> 23984 | H10: =SUM(H5:H9) -> 35378 | I10: =SUM(I5:I9) -> 42884 | J10: =SUM(J5:J9) -> 51078 | ... S10: =SUM(S5:S9) -> 66656.419
B12: Current Assets
B13: Inventories | C13: 16 | D13: 16 | E13: 21 | F13: 26 | G13: 10 | H13: 5 | I13: 8 | J13: 20 | K13: 28 | L13: 28 | M13: 21 | N13: 29 | O13: ='P&L'!T4*'Working Capital '!$T$13 -> 30.53292 | P13: ='P&L'!U4*'Working Capital '!$T$13 -> 32.14687 | Q13: ='P&L'!V4*'Working Capital '!$T$13 -> 33.846132 | R13: ='P&L'!W4*'Working Capital '!$T$13 -> 35.635215 | S13: ='P&L'!X4*'Working Capital '!$T$13 -> 37.518869 | T13: =N13/'P&L'!N4 -> 0.00010860569 | U13: Inventory % of revenue
B14: Trade receivables | C14: 20438 | D14: 24073 | E14: 22617 | F14: 24943 | G14: 27346 | H14: 30532 | I14: 30079 | J14: 41810 | K14: 49954 | L14: 53577 | M14: 59046 | N14: 67714 | O14: ='P&L'!T4*'Working Capital '!O21/365 -> 66240.157 | P14: ='P&L'!U4*'Working Capital '!P21/365 -> 69741.567 | Q14: ='P&L'!V4*'Working Capital '!Q21/365 -> 73428.059 | R14: ='P&L'!W4*'Working Capital '!R21/365 -> 77309.416 | S14: ='P&L'!X4*'Working Capital '!S21/365 -> 81395.939
B15: Total Current Assets | C15: =SUM(C13:C14) -> 20454 | D15: =SUM(D13:D14) -> 24089 | E15: =SUM(E13:E14) -> 22638 | F15: =SUM(F13:F14) -> 24969 | G15: =SUM(G13:G14) -> 27356 | H15: =SUM(H13:H14) -> 30537 | I15: =SUM(I13:I14) -> 30087 | J15: =SUM(J13:J14) -> 41830 | ... S15: =SUM(S13:S14) -> 81433.458
B17: Working Capital | C17: =C15-C10 -> -930 | D17: =D15-D10 -> 7357 | E17: =E15-E10 -> 6974 | F17: =F15-F10 -> 5439 | G17: =G15-G10 -> 3372 | H17: =H15-H10 -> -4841 | I17: =I15-I10 -> -12797 | J17: =J15-J10 -> -9248 | ... S17: =S15-S10 -> 14777.04
B18: Net Working Capital | C18: =C14+C13-C7-C8-C9 -> -744 | D18: =D14+D13-D7-D8-D9 -> 7470 | E18: =E14+E13-E7-E8-E9 -> 7174 | F18: =F14+F13-F7-F8-F9 -> 5620 | G18: =G14+G13-G7-G8-G9 -> 3416 | H18: =H14+H13-H7-H8-H9 -> 3333 | I18: =I14+I13-I7-I8-I9 -> -5002 | J18: =J14+J13-J7-J8-J9 -> -1430 | ... N18: =N14+N13-N7-N8-N9 -> 6337 | O18: =(O14+O13-O7-O8-O9) -> 12205.18 | P18: =P14+P13-P7-P8-P9 -> 15006.046 | Q18: =Q14+Q13-Q7-Q8-Q9 -> 17957.046 | R18: =R14+R13-R7-R8-R9 -> 21066.221 | S18: =S14+S13-S7-S8-S9 -> 24342.04
C20: 42064 | D20: 42430 | E20: 42795 | F20: 43160 | G20: 43525 | H20: 43891 | I20: 44256 | J20: 44621 | K20: 44986 | L20: 45352 | M20: 45717 | N20: 46082 | O20: 46447 | P20: 46813 | Q20: 47178 | R20: 47543 | S20: 47908
B21: Debtor Days | C21: 79 | D21: 81 | E21: 70 | F21: 74 | G21: 68 | H21: 71 | I21: 67 | J21: 80 | K21: 81 | L21: 81 | M21: 84 | N21: 93 | O21: =AVERAGE($L$21:$N$21) -> 86 | P21: =AVERAGE($L$21:$N$21) -> 86 | Q21: =AVERAGE($L$21:$N$21) -> 86 | R21: =AVERAGE($L$21:$N$21) -> 86 | S21: =AVERAGE($L$21:$N$21) -> 86
B22: Inventory Days
B23: Days Payable | C23: =C7/'P&L Detail'!C6*365 -> 45.937763 | D23: =D7/'P&L Detail'!D6*365 -> 35.302043 | E23: =E7/'P&L Detail'!E6*365 -> 20.901582 | F23: =F7/'P&L Detail'!F6*365 -> 20.524904 | G23: =G7/'P&L Detail'!G6*365 -> 21.471993 | H23: =H7/'P&L Detail'!H6*365 -> 21.421978 | I23: =I7/'P&L Detail'!I6*365 -> 24.388979 | J23: =J7/'P&L Detail'!J6*365 -> 21.171511 | ... N23: =N7/'P&L Detail'!N6*365 -> 27.77123 | O23: =AVERAGE($L$23:$N$23) -> 25.138863 | P23: =AVERAGE($L$23:$N$23) -> 25.138863 | Q23: =AVERAGE($L$23:$N$23) -> 25.138863 | R23: =AVERAGE($L$23:$N$23) -> 25.138863 | S23: =AVERAGE($L$23:$N$23) -> 25.138863
B24: Cash Conversion Cycle | C24: 79 | D24: 81 | E24: 70 | F24: 74 | G24: 68 | H24: 71 | I24: 67 | J24: 80 | K24: 81 | L24: 81 | M24: 84 | N24: 93 | O24: =AVERAGE($L$24:$N$24) -> 86 | P24: =AVERAGE($L$24:$N$24) -> 86 | Q24: =AVERAGE($L$24:$N$24) -> 86 | R24: =AVERAGE($L$24:$N$24) -> 86 | S24: =AVERAGE($L$24:$N$24) -> 86
B25: Working Capital Days | C25: 33 | D25: 62 | E25: 62 | F25: 61 | G25: 70 | H25: 64 | I25: 59 | J25: 33 | K25: 30 | L25: 34 | M25: 34 | N25: 38 | O25: =AVERAGE($L$25:$N$25) -> 35.333333 | P25: =AVERAGE($L$25:$N$25) -> 35.333333 | Q25: =AVERAGE($L$25:$N$25) -> 35.333333 | R25: =AVERAGE($L$25:$N$25) -> 35.333333 | S25: =AVERAGE($L$25:$N$25) -> 35.333333
B26: ROCE % | C26: 0.5 | D26: 0.51 | E26: 0.44 | F26: 0.39 | G26: 0.47 | H26: 0.47 | I26: 0.49 | J26: 0.54 | K26: 0.59 | L26: 0.64 | M26: 0.65 | N26: 0.63

Sheet Capital Structure
B2: Capital Structure
C3: 42064 | D3: 42430 | E3: 42795 | F3: 43160 | G3: 43525 | H3: 43891 | I3: 44256 | J3: 44621 | K3: 44986 | L3: 45352 | M3: 45717 | N3: 46082 | O3: 46447 | P3: 46813 | Q3: 47178 | R3: 47543 | S3: 47908
B4: Equity
B5: Equity Capital | C5: 196 | D5: 197 | E5: 197 | F5: 191 | G5: 375 | H5: 375 | I5: 370 | J5: 366 | K5: 366 | L5: 362 | M5: 362 | N5: 362 | O5: 362 | P5: 362 | Q5: 362 | R5: 362 | S5: 362
B6: Reserves | C6: 50439 | D6: 70875 | E6: 86017 | F6: 84937 | G6: 89071 | H6: 83751 | I6: 86063 | J6: 88773 | K6: 90058 | L6: 90127 | M6: 94394 | N6: 106878 | O6: ='P&L'!T13*(1-'P&L'!$N$15)+N6 -> 116612.48 | P6: ='P&L'!U13*(1-'P&L'!$N$15)+O6 -> 126697.35 | Q6: ='P&L'!V13*(1-'P&L'!$N$15)+P6 -> 137145.23 | R6: ='P&L'!W13*(1-'P&L'!$N$15)+Q6 -> 147969.18 | S6: ='P&L'!X13*(1-'P&L'!$N$15)+R6 -> 159182.74
B7: Total Equity | C7: =SUM(C5:C6) -> 50635 | D7: =SUM(D5:D6) -> 71072 | E7: =SUM(E5:E6) -> 86214 | F7: =SUM(F5:F6) -> 85128 | G7: =SUM(G5:G6) -> 89446 | H7: =SUM(H5:H6) -> 84126 | I7: =SUM(I5:I6) -> 86433 | J7: =SUM(J5:J6) -> 89139 | ... S7: =SUM(S5:S6) -> 159544.74
B9: Debt
B10: Long term Borrowings | C10: 114 | D10: 83 | E10: 71 | F10: 54 | G10: 44 | H10: 0 | I10: 0 | J10: 0 | K10: 0 | L10: 0 | M10: 0 | N10: 0 | O10: 0 | P10: 0 | Q10: 0 | R10: 0 | S10: 0
B11: Short term Borrowings | C11: 186 | D11: 113 | E11: 200 | F11: 181 | G11: 0 | H11: 0 | I11: 0 | J11: 0 | K11: 0 | L11: 0 | M11: 0 | N11: 0 | O11: 0 | P11: 0 | Q11: 0 | R11: 0 | S11: 0
B12: Lease Liabilities | C12: 0 | D12: 0 | E12: 0 | F12: 0 | G12: 44 | H12: 8174 | I12: 7795 | J12: 7818 | K12: 7688 | L12: 8021 | M12: 9392 | N12: 11283 | O12: 11283 | P12: 11283 | Q12: 11283 | R12: 11283 | S12: 11283
B13: Other Borrowings | C13: 58 | D13: 49 | E13: 18 | F13: 12 | G13: -26 | H13: 0 | I13: 0 | J13: 0 | K13: 0 | L13: 0 | M13: 0 | N13: 0 | O13: 0 | P13: 0 | Q13: 0 | R13: 0 | S13: 0
B14: Total Gross Debt | C14: =SUM(C10:C13) -> 358 | D14: =SUM(D10:D13) -> 245 | E14: =SUM(E10:E13) -> 289 | F14: =SUM(F10:F13) -> 247 | G14: =SUM(G10:G13) -> 62 | H14: =SUM(H10:H13) -> 8174 | I14: =SUM(I10:I13) -> 7795 | J14: =SUM(J10:J13) -> 7818 | ... S14: =SUM(S10:S13) -> 11283
B15: Cash Equivalents | C15: 18556 | D15: 6788 | E15: 4149 | F15: 7161 | G15: 12848 | H15: 9666 | I15: 9329 | J15: 18221 | K15: 11032 | L15: 13286 | M15: 15463 | N15: 12908 | O15: 12908 | P15: 12908 | Q15: 12908 | R15: 12908 | S15: 12908
B16: Net Debt | C16: =C14-C15 -> -18198 | D16: =D14-D15 -> -6543 | E16: =E14-E15 -> -3860 | F16: =F14-F15 -> -6914 | G16: =G14-G15 -> -12786 | H16: =H14-H15 -> -1492 | I16: =I14-I15 -> -1534 | J16: =J14-J15 -> -10403 | ... S16: =S14-S15 -> -1625

Sheet WACC
B2: WACC
C3: 42064 | D3: 42430 | E3: 42795 | F3: 43160 | G3: 43525 | H3: 43891 | I3: 44256 | J3: 44621 | K3: 44986 | L3: 45352 | M3: 45717 | N3: 46082 | O3: 46447 | P3: 46813 | Q3: 47178 | R3: 47543 | S3: 47908
B4: Debt | C4: ='Capital Structure'!C14 -> 358 | D4: ='Capital Structure'!D14 -> 245 | E4: ='Capital Structure'!E14 -> 289 | F4: ='Capital Structure'!F14 -> 247 | G4: ='Capital Structure'!G14 -> 62 | H4: ='Capital Structure'!H14 -> 8174 | I4: ='Capital Structure'!I14 -> 7795 | J4: ='Capital Structure'!J14 -> 7818 | ... S4: ='Capital Structure'!S14 -> 11283
B5: Equity | C5: ='Capital Structure'!C7 -> 50635 | D5: ='Capital Structure'!D7 -> 71072 | E5: ='Capital Structure'!E7 -> 86214 | F5: ='Capital Structure'!F7 -> 85128 | G5: ='Capital Structure'!G7 -> 89446 | H5: ='Capital Structure'!H7 -> 84126 | I5: ='Capital Structure'!I7 -> 86433 | J5: ='Capital Structure'!J7 -> 89139 | ... S5: ='Capital Structure'!S7 -> 159544.74
B7: Debt / (Debt + Equity) | C7: =C4/(C4+C5) -> 0.0070205715 | D7: =D4/(D4+D5) -> 0.003435366 | E7: =E4/(E4+E5) -> 0.0033409246 | F7: =F4/(F4+F5) -> 0.0028931186 | G7: =G4/(G4+G5) -> 0.00069267552 | H7: =H4/(H4+H5) -> 0.088559047 | I7: =I4/(I4+I5) -> 0.08272488 | J7: =J4/(J4+J5) -> 0.080633683 | ... S7: =S4/(S4+S5) -> 0.066048992
B8: Equity / (Debt + Equity) | C8: =C5/(C4+C5) -> 0.99297943 | D8: =D5/(D4+D5) -> 0.99656463 | E8: =E5/(E4+E5) -> 0.99665908 | F8: =F5/(F4+F5) -> 0.99710688 | G8: =G5/(G4+G5) -> 0.99930732 | H8: =H5/(H4+H5) -> 0.91144095 | I8: =I5/(I4+I5) -> 0.91727512 | J8: =J5/(J4+J5) -> 0.91936632 | ... N8: =N5/(N4+N5) -> 0.90480329 | O8: =O5/(O5+O4) -> 0.91202852 | P8: =P5/(P5+P4) -> 0.91844146 | Q8: =Q5/(Q5+Q4) -> 0.92416841 | R8: =R5/(R5+R4) -> 0.92931079 | S8: =S5/(S5+S4) -> 0.93395101
B10: Cost of equity | C10: 10.05 | D10: 9.15 | E10: 9.04 | F10: 9.8 | G10: 10.5 | H10: 10.38 | I10: 12.17 | J10: 12.86 | K10: 13.15 | L10: 13.75 | M10: 14.39 | N10: 15.11 | O10: 15.11 | P10: 15.11 | Q10: 15.11 | R10: 15.11 | S10: 15.11
B11: Cost of debt | C11: - | D11: - | E11: - | F11: - | G11: - | H11: - | I11: - | J11: - | K11: - | L11: - | M11: - | N11: - | O11: - | P11: - | Q11: - | R11: - | S11: -
B13: WACC | C13: =C8*C10 -> 9.9794433 | D13: =D8*D10 -> 9.1185664 | E13: =E8*E10 -> 9.009798 | F13: =F8*F10 -> 9.7716474 | G13: =G8*G10 -> 10.492727 | H13: =H8*H10 -> 9.4607571 | I13: =I8*I10 -> 11.163238 | J13: =J8*J10 -> 11.823051 | ... S13: =S8*S10 -> 14.112

Sheet DCF 
B1: TCS DCF Model
B3: Perpetual Growth Rate | C3: 0.04
B4: Shares Outstanding | C4: 361.80875 | D4: crore shares
B6: Year ---> | C6: 1 | D6: 2 | E6: 3 | F6: 4 | G6: 5
C7: 46447 | D7: 46813 | E7: 47178 | F7: 47543 | G7: 47908
B8: Sales | C8: ='P&L'!T4 -> 281135.55 | D8: ='P&L'!U4 -> 295996.18 | E8: ='P&L'!V4 -> 311642.34 | F8: ='P&L'!W4 -> 328115.54 | G8: ='P&L'!X4 -> 345459.51
B9: EBIT | C9: ='P&L'!T6 -> 76829.784 | D9: ='P&L'!U6 -> 81532.855 | E9: ='P&L'!V6 -> 86523.822 | F9: ='P&L'!W6 -> 91820.306 | G9: ='P&L'!X6 -> 97441.01
B10: EBIT (1 - T) | C10: =C9*0.76 -> 58390.636 | D10: =D9*0.76 -> 61964.97 | E10: =E9*0.76 -> 65758.105 | F10: =F9*0.76 -> 69783.433 | G10: =G9*0.76 -> 74055.168
B11: Depreciation | C11: ='P&L'!T10 -> 5871.9675 | D11: ='P&L'!U10 -> 6201.4393 | E11: ='P&L'!V10 -> 6549.3975 | F11: ='P&L'!W10 -> 6916.8794 | G11: ='P&L'!X10 -> 7304.9804
B12: less: Capex | C12: =-'Cash Flow '!T12 -> 5235.1795 | D12: =-'Cash Flow '!U12 -> 6610.4931 | E12: =-'Cash Flow '!V12 -> 8347.11 | F12: =-'Cash Flow '!W12 -> 10539.947 | G12: =-'Cash Flow '!X12 -> 13308.855
B13: Less: NWC | C13: ='Working Capital '!O18-'Working Capital '!N18 -> 5868.1802 | D13: ='Working Capital '!P18-'Working Capital '!O18 -> 2800.8657 | E13: ='Working Capital '!Q18-'Working Capital '!P18 -> 2951.0002 | F13: ='Working Capital '!R18-'Working Capital '!Q18 -> 3109.1745 | G13: ='Working Capital '!S18-'Working Capital '!R18 -> 3275.819
B14: FCFF | C14: =C10+C11-C12-C13 -> 53159.243 | D14: =D10+D11-D12-D13 -> 58755.051 | E14: =E10+E11-E12-E13 -> 61009.392 | F14: =F10+F11-F12-F13 -> 63051.191 | G14: =G10+G11-G12-G13 -> 64775.474
B15: WACC | C15: =WACC!O13/100 -> 0.13780751 | D15: =WACC!P13/100 -> 0.1387765 | E15: =WACC!Q13/100 -> 0.13964185 | F15: =WACC!R13/100 -> 0.14041886 | G15: =WACC!S13/100 -> 0.14112
B16: Terminal Value | G16: =(G14*(1+C3))/(G15-C3) -> 666203.47
B17: PV OF FCFF | C17: =C14/(1+C15)^C6 -> 46720.77 | D17: =D14/(1+D15)^D6 -> 45307.303 | E17: =E14/(1+E15)^E6 -> 41218.438 | F17: =F14/(1+F15)^F6 -> 37276.551 | G17: =G14/(1+G15)^G6 -> 33477.577
B18: PV OF Terminal Value | G18: =G16/(1+G15)^G6 -> 344310.53
B21: Perpetuity Growth Rate-Based Valuation
B22: Total PV of Cash Flows | F22: =SUM(C17:G17) -> 204000.64
B23: PV of Terminal value | F23: =G18 -> 344310.53
B24: Enterprise Value | F24: =SUM(F22:F23) -> 548311.17
B25: less: Debt | F25: ='Balance Sheet Detail'!N7+'Balance Sheet Detail'!N8+'Balance Sheet Detail'!N9+'Balance Sheet Detail'!N10 -> 11283
B26: Add: Cash | F26: ='Balance Sheet Detail'!N30+'Balance Sheet Detail'!N37 -> 46896
B27: Equity Value | F27: =F24+F26-F25 -> 583924.17
B28: Value per share | F28: =F27/C4 -> 1613.9028

Sheet Comparable Company valuation
B2: Comparable Company valuation
B3: Company | C3: EV/EBITDA | D3: Enterprise Value/Revenue
B4: Infosys | C4: 7.98 | D4: 2.02
B5: HCLTech | C5: 11.51 | D5: 2.42
B6: Wipro | C6: 6.81 | D6: 1.52
B8: Average | C8: =AVERAGE(C4:C6) -> 8.7666667 | D8: =AVERAGE(D4:D6) -> 1.9866667
B12: TCS EBITDA | C12: ='P&L Detail'!N11+'P&L Detail'!N17 -> 77958
B13: TCS EV | C13: =C12*C8 -> 683431.8
B15: TCS Revenue | C15: ='P&L Detail'!N4 -> 267021
B16: TCS EV | C16: =C15*D8 -> 530481.72

Sheet Sensitivity Analysis
B2: Sensitivity Analysis Table
B3: Enterprise Value
B4: WACC ↓ / Terminal Growth → | C4: 0.04 | D4: 0.05 | E4: 0.06
B5: 0.14112 | C5: 548311.17 | D5: 589771.68 | E5: 641454.2

Sheet Compare with market price
B2: Compare with Market Price
B4: TCS Market Price | C4: 2080.5
B5: DCF Price | C5: ='DCF '!F28 -> 1613.9028
B7: Intrinsic Value < Market Price

Sheet sources
B2: Sources
B4: Company Sources
B5: Screener
B6: Yahoo Finance
